arviz_plots/__init__.py
arviz_plots/_version.py
arviz_plots/plot_collection.py
arviz_plots/plot_matrix.py
arviz_plots/py.typed
arviz_plots/style.py
arviz_plots/backend/__init__.py
arviz_plots/backend/alias_utils.py
arviz_plots/backend/bokeh/__init__.py
arviz_plots/backend/bokeh/core.py
arviz_plots/backend/bokeh/legend.py
arviz_plots/backend/matplotlib/__init__.py
arviz_plots/backend/matplotlib/core.py
arviz_plots/backend/matplotlib/legend.py
arviz_plots/backend/none/__init__.py
arviz_plots/backend/none/core.py
arviz_plots/backend/none/legend.py
arviz_plots/backend/plotly/__init__.py
arviz_plots/backend/plotly/core.py
arviz_plots/backend/plotly/legend.py
arviz_plots/backend/plotly/templates.py
arviz_plots/plots/__init__.py
arviz_plots/plots/autocorr_plot.py
arviz_plots/plots/bf_plot.py
arviz_plots/plots/combine.py
arviz_plots/plots/compare_plot.py
arviz_plots/plots/convergence_dist_plot.py
arviz_plots/plots/dgof_dist_plot.py
arviz_plots/plots/dgof_plot.py
arviz_plots/plots/dist_plot.py
arviz_plots/plots/ecdf_plot.py
arviz_plots/plots/energy_plot.py
arviz_plots/plots/ess_plot.py
arviz_plots/plots/evolution_plot.py
arviz_plots/plots/forest_plot.py
arviz_plots/plots/khat_plot.py
arviz_plots/plots/lm_plot.py
arviz_plots/plots/loo_pit_plot.py
arviz_plots/plots/mcse_plot.py
arviz_plots/plots/pair_focus_plot.py
arviz_plots/plots/pair_plot.py
arviz_plots/plots/parallel_plot.py
arviz_plots/plots/pava_calibration_plot.py
arviz_plots/plots/pava_residual_plot.py
arviz_plots/plots/ppc_censored_plot.py
arviz_plots/plots/ppc_dist_plot.py
arviz_plots/plots/ppc_interval_plot.py
arviz_plots/plots/ppc_pit_plot.py
arviz_plots/plots/ppc_rootogram_plot.py
arviz_plots/plots/ppc_tstat.py
arviz_plots/plots/prior_posterior_plot.py
arviz_plots/plots/psense_dist_plot.py
arviz_plots/plots/psense_quantities_plot.py
arviz_plots/plots/rank_dist_plot.py
arviz_plots/plots/rank_plot.py
arviz_plots/plots/ridge_plot.py
arviz_plots/plots/trace_dist_plot.py
arviz_plots/plots/trace_plot.py
arviz_plots-0.8.0.dist-info/licenses/LICENSE
arviz_plots-0.8.0.dist-info/WHEEL
arviz_plots-0.8.0.dist-info/METADATA
arviz_plots-0.8.0.dist-info/RECORD
