Metadata-Version: 2.4
Name: arviz-plots
Version: 0.8.0
Summary: ArviZ-plots provides ready to use and composable plots for Bayesian Workflow.
Author-email: ArviZ team <arvizdevs@gmail.com>
Requires-Python: >=3.11
Classifier: Development Status :: 3 - Alpha
Classifier: Intended Audience :: Developers
Classifier: Intended Audience :: Science/Research
Classifier: Intended Audience :: Education
Classifier: Framework :: Matplotlib
Classifier: License :: OSI Approved :: Apache Software License
Classifier: Operating System :: OS Independent
Classifier: Programming Language :: Python
Classifier: Programming Language :: Python :: 3
Classifier: Programming Language :: Python :: 3.10
Classifier: Programming Language :: Python :: 3.11
Classifier: Programming Language :: Python :: 3.12
License-File: LICENSE
Requires-Dist: arviz-base>=0.8.1,<0.9.0
Requires-Dist: arviz-stats[xarray]>=0.8.0,<0.9.0
Requires-Dist: bokeh ; extra == "bokeh"
Requires-Dist: sphinx-book-theme ; extra == "doc"
Requires-Dist: myst-parser[linkify] ; extra == "doc"
Requires-Dist: myst-nb ; extra == "doc"
Requires-Dist: sphinx-copybutton ; extra == "doc"
Requires-Dist: numpydoc ; extra == "doc"
Requires-Dist: sphinx>=6 ; extra == "doc"
Requires-Dist: sphinx-design ; extra == "doc"
Requires-Dist: jupyter-sphinx ; extra == "doc"
Requires-Dist: h5netcdf ; extra == "doc"
Requires-Dist: plotly<6 ; extra == "doc"
Requires-Dist: matplotlib ; extra == "matplotlib"
Requires-Dist: plotly ; extra == "plotly"
Requires-Dist: webcolors ; extra == "plotly"
Requires-Dist: hypothesis ; extra == "test"
Requires-Dist: pytest ; extra == "test"
Requires-Dist: pytest-cov ; extra == "test"
Requires-Dist: h5netcdf ; extra == "test"
Requires-Dist: kaleido ; extra == "test"
Project-URL: documentation, https://arviz-plots.readthedocs.io
Project-URL: funding, https://opencollective.com/arviz
Project-URL: source, https://github.com/arviz-devs/arviz-plots
Project-URL: tracker, https://github.com/arviz-devs/arviz-plots/issues
Provides-Extra: bokeh
Provides-Extra: doc
Provides-Extra: matplotlib
Provides-Extra: plotly
Provides-Extra: test
